CHANGES.txt
DEPENDENCES.txt
README.txt
TODO.txt
setup.py
src/ng/__init__.py
src/ng.app.registry.egg-info/PKG-INFO
src/ng.app.registry.egg-info/SOURCES.txt
src/ng.app.registry.egg-info/dependency_links.txt
src/ng.app.registry.egg-info/namespace_packages.txt
src/ng.app.registry.egg-info/not-zip-safe
src/ng.app.registry.egg-info/requires.txt
src/ng.app.registry.egg-info/top_level.txt
src/ng/app/__init__.py
src/ng/app/registry/__init__.py
src/ng/app/registry/configure.zcml
src/ng/app/registry/interfaces.py
src/ng/app/registry/ng.app.registry.txt
src/ng/app/registry/registry.py
src/ng/app/registry/registryint.py
src/ng/app/registry/registrytext.py
src/ng/app/registry/registrytextline.py
src/ng/app/registry/registryvocabulary.py
src/ng/app/registry/browser/__init__.py
src/ng/app/registry/browser/configure.zcml
src/ng/app/registry/browser/registryedit.py
src/ng/app/registry/etc/ng.app.registry-configure.zcml
src/ng/app/registry/registryadapter/__init__.py
src/ng/app/registry/registryadapter/configure.zcml
src/ng/app/registry/registryadapter/registryadapter.py
src/ng/app/registry/registrynamespace/__init__.py
src/ng/app/registry/registrynamespace/configure.zcml
src/ng/app/registry/registrynamespace/ng.registry.namespace.txt
src/ng/app/registry/registrynamespace/registrynamespace.py
